pystratum_backend/Backend.py
pystratum_backend/ConstantWorker.py
pystratum_backend/Helper/Terminal.py
pystratum_backend/Helper/__init__.py
pystratum_backend/RoutineLoaderWorker.py
pystratum_backend/RoutineWrapperGeneratorWorker.py
pystratum_backend/StratumIO.py
pystratum_backend/__init__.py
pystratum_backend-2.1.0.dist-info/LICENSE.md
pystratum_backend-2.1.0.dist-info/METADATA
pystratum_backend-2.1.0.dist-info/WHEEL
pystratum_backend-2.1.0.dist-info/RECORD
